Metadata-Version: 2.1
Name: pyxbe
Version: 1.0.3
Summary: Library to work with XBE files
Home-page: https://github.com/mborgerson/pyxbe
Author: Matt Borgerson
Author-email: contact@mborgerson.com
License: MIT
Platform: UNKNOWN
Classifier: License :: OSI Approved :: MIT License
Classifier: Programming Language :: Python :: 3
Classifier: Programming Language :: Python :: 3 :: Only
Requires-Python: >=3.8
Provides-Extra: docs
